<?xml version="1.0" encoding="UTF-8"?>
<jobs>
  <job>
    <job-id>135500362</job-id>
    <job-title>Врач клинической лабораторной диагностики (Красногорск, пгт. Отрадное)</job-title>
    <job-employer>Группа компаний МЕДСИ</job-employer>
    <job-area>Москва</job-area>
    <job-url>https://vakansa24.ru/vacancy.html?id=135500362</job-url>
    <job-date>2026-07-23 06:26</job-date>
    <salary><to>150000</to><currency>RUR</currency></salary>
    <job-description><![CDATA[Описание отсутствует]]></job-description>
  </job>
  <job>
    <job-id>135435975</job-id>
    <job-title>Кассир-бариста (м. Шаболовская)</job-title>
    <job-employer>Печорин Групп</job-employer>
    <job-area>Москва</job-area>
    <job-url>https://vakansa24.ru/vacancy.html?id=135435975</job-url>
    <job-date>2026-07-23 06:26</job-date>
    <salary><from>90000</from><currency>RUR</currency></salary>
    <job-description><![CDATA[Описание отсутствует]]></job-description>
  </job>
  <job>
    <job-id>135500361</job-id>
    <job-title>Тайный покупатель</job-title>
    <job-employer>Сервизория</job-employer>
    <job-area>Пыталово</job-area>
    <job-url>https://vakansa24.ru/vacancy.html?id=135500361</job-url>
    <job-date>2026-07-23 06:26</job-date>
    
    <job-description><![CDATA[Описание отсутствует]]></job-description>
  </job>
  <job>
    <job-id>135141223</job-id>
    <job-title>Маркировщик корейской косметики на складском комплексе (г. Новосибирск)</job-title>
    <job-employer>СИМПЛЕКС</job-employer>
    <job-area>Томск</job-area>
    <job-url>https://vakansa24.ru/vacancy.html?id=135141223</job-url>
    <job-date>2026-07-23 06:26</job-date>
    <salary><from>145000</from><to>198000</to><currency>RUR</currency></salary>
    <job-description><![CDATA[Описание отсутствует]]></job-description>
  </job>
  <job>
    <job-id>135500360</job-id>
    <job-title>Слесарь по ремонту горно-транспортного оборудования (автослесарь)</job-title>
    <job-employer>Цементум Центр</job-employer>
    <job-area>Ферзиково</job-area>
    <job-url>https://vakansa24.ru/vacancy.html?id=135500360</job-url>
    <job-date>2026-07-23 06:26</job-date>
    <salary><from>117000</from><to>117000</to><currency>RUR</currency></salary>
    <job-description><![CDATA[Описание отсутствует]]></job-description>
  </job>
  <job>
    <job-id>135098564</job-id>
    <job-title>Помощник технического директора</job-title>
    <job-employer>МТС</job-employer>
    <job-area>Казань</job-area>
    <job-url>https://vakansa24.ru/vacancy.html?id=135098564</job-url>
    <job-date>2026-07-23 06:26</job-date>
    <salary><from>62000</from><currency>RUR</currency></salary>
    <job-description><![CDATA[Описание отсутствует]]></job-description>
  </job>
  <job>
    <job-id>135500359</job-id>
    <job-title>Ведущий специалист отдела кадров</job-title>
    <job-employer>СКМ</job-employer>
    <job-area>Нижневартовск</job-area>
    <job-url>https://vakansa24.ru/vacancy.html?id=135500359</job-url>
    <job-date>2026-07-23 06:26</job-date>
    <salary><from>60000</from><to>80000</to><currency>RUR</currency></salary>
    <job-description><![CDATA[Описание отсутствует]]></job-description>
  </job>
  <job>
    <job-id>132912921</job-id>
    <job-title>Кассир-продавец/кассир-бариста (д.Захарово, Эстейт молл)</job-title>
    <job-employer>Печорин Групп</job-employer>
    <job-area>Павловская Слобода (Московская область)</job-area>
    <job-url>https://vakansa24.ru/vacancy.html?id=132912921</job-url>
    <job-date>2026-07-23 06:26</job-date>
    <salary><from>7000</from><currency>RUR</currency></salary>
    <job-description><![CDATA[Описание отсутствует]]></job-description>
  </job>
  <job>
    <job-id>135500358</job-id>
    <job-title>Укладчик-упаковщик</job-title>
    <job-employer>Енисей</job-employer>
    <job-area>Красноярск</job-area>
    <job-url>https://vakansa24.ru/vacancy.html?id=135500358</job-url>
    <job-date>2026-07-23 06:26</job-date>
    <salary><from>52500</from><to>70000</to><currency>RUR</currency></salary>
    <job-description><![CDATA[Описание отсутствует]]></job-description>
  </job>
  <job>
    <job-id>135500356</job-id>
    <job-title>Грузчик</job-title>
    <job-employer>ГП Калугафармация</job-employer>
    <job-area>Калуга</job-area>
    <job-url>https://vakansa24.ru/vacancy.html?id=135500356</job-url>
    <job-date>2026-07-23 06:26</job-date>
    <salary><from>46500</from><currency>RUR</currency></salary>
    <job-description><![CDATA[Описание отсутствует]]></job-description>
  </job>
  <job>
    <job-id>134707642</job-id>
    <job-title>Супервайзер водителей (м. Озерная)</job-title>
    <job-employer>Нила Спрингс</job-employer>
    <job-area>Москва</job-area>
    <job-url>https://vakansa24.ru/vacancy.html?id=134707642</job-url>
    <job-date>2026-07-23 06:26</job-date>
    <salary><from>120000</from><currency>RUR</currency></salary>
    <job-description><![CDATA[Описание отсутствует]]></job-description>
  </job>
  <job>
    <job-id>134476306</job-id>
    <job-title>ASO-специалист</job-title>
    <job-employer>Банки.ру</job-employer>
    <job-area>Москва</job-area>
    <job-url>https://vakansa24.ru/vacancy.html?id=134476306</job-url>
    <job-date>2026-07-23 06:26</job-date>
    
    <job-description><![CDATA[Описание отсутствует]]></job-description>
  </job>
  <job>
    <job-id>134161215</job-id>
    <job-title>Кассир-продавец/Кассир-бариста (д.Захарово, Эстейт молл)</job-title>
    <job-employer>Печорин Групп</job-employer>
    <job-area>Истра (Московская область)</job-area>
    <job-url>https://vakansa24.ru/vacancy.html?id=134161215</job-url>
    <job-date>2026-07-23 06:26</job-date>
    <salary><from>7000</from><currency>RUR</currency></salary>
    <job-description><![CDATA[Описание отсутствует]]></job-description>
  </job>
  <job>
    <job-id>135500354</job-id>
    <job-title>Стоматолог детский</job-title>
    <job-employer>Анидент 22</job-employer>
    <job-area>Москва</job-area>
    <job-url>https://vakansa24.ru/vacancy.html?id=135500354</job-url>
    <job-date>2026-07-23 06:26</job-date>
    <salary><from>180000</from><currency>RUR</currency></salary>
    <job-description><![CDATA[Описание отсутствует]]></job-description>
  </job>
  <job>
    <job-id>135500352</job-id>
    <job-title>Машинист бульдозера (CAT D-9R D-275)</job-title>
    <job-employer>Высочайший</job-employer>
    <job-area>Уфа</job-area>
    <job-url>https://vakansa24.ru/vacancy.html?id=135500352</job-url>
    <job-date>2026-07-23 06:26</job-date>
    <salary><from>249000</from><currency>RUR</currency></salary>
    <job-description><![CDATA[Описание отсутствует]]></job-description>
  </job>
  <job>
    <job-id>135500351</job-id>
    <job-title>Продавец-консультант в салон связи</job-title>
    <job-employer>билайн</job-employer>
    <job-area>Нарьян-Мар</job-area>
    <job-url>https://vakansa24.ru/vacancy.html?id=135500351</job-url>
    <job-date>2026-07-23 06:26</job-date>
    <salary><from>77000</from><to>102000</to><currency>RUR</currency></salary>
    <job-description><![CDATA[Описание отсутствует]]></job-description>
  </job>
  <job>
    <job-id>134473385</job-id>
    <job-title>Бригадир (Аллегро)</job-title>
    <job-employer>ЕВРАЗ</job-employer>
    <job-area>Нижний Тагил</job-area>
    <job-url>https://vakansa24.ru/vacancy.html?id=134473385</job-url>
    <job-date>2026-07-23 06:26</job-date>
    <salary><from>85000</from><to>85000</to><currency>RUR</currency></salary>
    <job-description><![CDATA[Описание отсутствует]]></job-description>
  </job>
  <job>
    <job-id>134473383</job-id>
    <job-title>Бригадир (Аллегро)</job-title>
    <job-employer>ЕВРАЗ</job-employer>
    <job-area>Верхняя Салда</job-area>
    <job-url>https://vakansa24.ru/vacancy.html?id=134473383</job-url>
    <job-date>2026-07-23 06:26</job-date>
    <salary><from>85000</from><to>85000</to><currency>RUR</currency></salary>
    <job-description><![CDATA[Описание отсутствует]]></job-description>
  </job>
  <job>
    <job-id>135500350</job-id>
    <job-title>Судокорпусник-ремонтник</job-title>
    <job-employer>Азово-Черноморский филиал ФГБУ Морская спасательная служба</job-employer>
    <job-area>Новороссийск</job-area>
    <job-url>https://vakansa24.ru/vacancy.html?id=135500350</job-url>
    <job-date>2026-07-23 06:26</job-date>
    <salary><from>70000</from><to>85000</to><currency>RUR</currency></salary>
    <job-description><![CDATA[Описание отсутствует]]></job-description>
  </job>
  <job>
    <job-id>135500347</job-id>
    <job-title>Машинист буровой установки (геологоразведка)</job-title>
    <job-employer>СГП-Геология</job-employer>
    <job-area>Прокопьевск</job-area>
    <job-url>https://vakansa24.ru/vacancy.html?id=135500347</job-url>
    <job-date>2026-07-23 06:26</job-date>
    <salary><from>300000</from><currency>RUR</currency></salary>
    <job-description><![CDATA[Описание отсутствует]]></job-description>
  </job>
  <job>
    <job-id>135500348</job-id>
    <job-title>Машинист буровой установки (геологоразведка)</job-title>
    <job-employer>СГП-Геология</job-employer>
    <job-area>Междуреченск</job-area>
    <job-url>https://vakansa24.ru/vacancy.html?id=135500348</job-url>
    <job-date>2026-07-23 06:26</job-date>
    <salary><from>300000</from><currency>RUR</currency></salary>
    <job-description><![CDATA[Описание отсутствует]]></job-description>
  </job>
  <job>
    <job-id>135500349</job-id>
    <job-title>Машинист буровой установки (геологоразведка)</job-title>
    <job-employer>СГП-Геология</job-employer>
    <job-area>Анжеро-Судженск</job-area>
    <job-url>https://vakansa24.ru/vacancy.html?id=135500349</job-url>
    <job-date>2026-07-23 06:26</job-date>
    <salary><from>300000</from><currency>RUR</currency></salary>
    <job-description><![CDATA[Описание отсутствует]]></job-description>
  </job>
  <job>
    <job-id>132915682</job-id>
    <job-title>Инженер по обеспечению операционной деятельности</job-title>
    <job-employer>МТС</job-employer>
    <job-area>Казань</job-area>
    <job-url>https://vakansa24.ru/vacancy.html?id=132915682</job-url>
    <job-date>2026-07-23 06:26</job-date>
    <salary><from>62000</from><currency>RUR</currency></salary>
    <job-description><![CDATA[Описание отсутствует]]></job-description>
  </job>
  <job>
    <job-id>133733337</job-id>
    <job-title>Водитель-экспедитор категории С (м. Бухарестская)</job-title>
    <job-employer>Нила Спрингс</job-employer>
    <job-area>Санкт-Петербург</job-area>
    <job-url>https://vakansa24.ru/vacancy.html?id=133733337</job-url>
    <job-date>2026-07-23 06:26</job-date>
    <salary><from>120000</from><to>200000</to><currency>RUR</currency></salary>
    <job-description><![CDATA[Описание отсутствует]]></job-description>
  </job>
  <job>
    <job-id>134751757</job-id>
    <job-title>Электромонтер по ремонту и обслуживанию электрооборудования 5 разряда</job-title>
    <job-employer>НПО Радиоэлектроника им. В.И. Шимко</job-employer>
    <job-area>Казань</job-area>
    <job-url>https://vakansa24.ru/vacancy.html?id=134751757</job-url>
    <job-date>2026-07-23 06:26</job-date>
    <salary><from>85053</from><to>99229</to><currency>RUR</currency></salary>
    <job-description><![CDATA[Описание отсутствует]]></job-description>
  </job>
  <job>
    <job-id>135500346</job-id>
    <job-title>Сварщик</job-title>
    <job-employer>Дельта</job-employer>
    <job-area>Шахты</job-area>
    <job-url>https://vakansa24.ru/vacancy.html?id=135500346</job-url>
    <job-date>2026-07-23 06:25</job-date>
    <salary><from>111630</from><currency>RUR</currency></salary>
    <job-description><![CDATA[Описание отсутствует]]></job-description>
  </job>
  <job>
    <job-id>135032916</job-id>
    <job-title>Агент по недвижимости</job-title>
    <job-employer>Этажи Центр</job-employer>
    <job-area>Тула</job-area>
    <job-url>https://vakansa24.ru/vacancy.html?id=135032916</job-url>
    <job-date>2026-07-23 06:25</job-date>
    <salary><from>150000</from><currency>RUR</currency></salary>
    <job-description><![CDATA[Описание отсутствует]]></job-description>
  </job>
  <job>
    <job-id>134022165</job-id>
    <job-title>Инженер развития сети</job-title>
    <job-employer>МТС</job-employer>
    <job-area>Казань</job-area>
    <job-url>https://vakansa24.ru/vacancy.html?id=134022165</job-url>
    <job-date>2026-07-23 06:25</job-date>
    <salary><from>70000</from><currency>RUR</currency></salary>
    <job-description><![CDATA[Описание отсутствует]]></job-description>
  </job>
  <job>
    <job-id>135220112</job-id>
    <job-title>Менеджер кафе (м. Академическая)</job-title>
    <job-employer>Печорин Групп</job-employer>
    <job-area>Москва</job-area>
    <job-url>https://vakansa24.ru/vacancy.html?id=135220112</job-url>
    <job-date>2026-07-23 06:25</job-date>
    <salary><from>120000</from><currency>RUR</currency></salary>
    <job-description><![CDATA[Описание отсутствует]]></job-description>
  </job>
  <job>
    <job-id>134709608</job-id>
    <job-title>Заместитель главного бухгалтера</job-title>
    <job-employer>Миофарм</job-employer>
    <job-area>Москва</job-area>
    <job-url>https://vakansa24.ru/vacancy.html?id=134709608</job-url>
    <job-date>2026-07-23 06:25</job-date>
    
    <job-description><![CDATA[Описание отсутствует]]></job-description>
  </job>
  <job>
    <job-id>135500345</job-id>
    <job-title>Водитель легкового автомобиля</job-title>
    <job-employer>Росгосстрах</job-employer>
    <job-area>Рязань</job-area>
    <job-url>https://vakansa24.ru/vacancy.html?id=135500345</job-url>
    <job-date>2026-07-23 06:25</job-date>
    <salary><from>37800</from><to>37800</to><currency>RUR</currency></salary>
    <job-description><![CDATA[Описание отсутствует]]></job-description>
  </job>
  <job>
    <job-id>135500343</job-id>
    <job-title>Продавец-кассир</job-title>
    <job-employer>КАРИ</job-employer>
    <job-area>Краснодар</job-area>
    <job-url>https://vakansa24.ru/vacancy.html?id=135500343</job-url>
    <job-date>2026-07-23 06:25</job-date>
    <salary><from>45000</from><to>50000</to><currency>RUR</currency></salary>
    <job-description><![CDATA[Описание отсутствует]]></job-description>
  </job>
  <job>
    <job-id>135194135</job-id>
    <job-title>Транспортировщик</job-title>
    <job-employer>Компания Металл Профиль, OOO</job-employer>
    <job-area>Нововоронеж</job-area>
    <job-url>https://vakansa24.ru/vacancy.html?id=135194135</job-url>
    <job-date>2026-07-23 06:25</job-date>
    <salary><from>75000</from><currency>RUR</currency></salary>
    <job-description><![CDATA[Описание отсутствует]]></job-description>
  </job>
  <job>
    <job-id>135500342</job-id>
    <job-title>Электромеханик</job-title>
    <job-employer>Кадровый центр «ПРЕЗИДЕНТ»</job-employer>
    <job-area>Талдом (Московская область)</job-area>
    <job-url>https://vakansa24.ru/vacancy.html?id=135500342</job-url>
    <job-date>2026-07-23 06:25</job-date>
    <salary><from>90000</from><currency>RUR</currency></salary>
    <job-description><![CDATA[Описание отсутствует]]></job-description>
  </job>
  <job>
    <job-id>135500341</job-id>
    <job-title>Тайный покупатель (г. Богданович)</job-title>
    <job-employer>Живика, аптечная сеть</job-employer>
    <job-area>Богданович</job-area>
    <job-url>https://vakansa24.ru/vacancy.html?id=135500341</job-url>
    <job-date>2026-07-23 06:25</job-date>
    <salary><from>16000</from><currency>RUR</currency></salary>
    <job-description><![CDATA[Описание отсутствует]]></job-description>
  </job>
  <job>
    <job-id>135500340</job-id>
    <job-title>Водитель автомобиля</job-title>
    <job-employer>ПРОГРЕСС</job-employer>
    <job-area>Липецк</job-area>
    <job-url>https://vakansa24.ru/vacancy.html?id=135500340</job-url>
    <job-date>2026-07-23 06:25</job-date>
    
    <job-description><![CDATA[Описание отсутствует]]></job-description>
  </job>
  <job>
    <job-id>135500339</job-id>
    <job-title>Руководитель отдела продаж (застройщика), Майкоп</job-title>
    <job-employer>СК ЕВРОСТРОЙ</job-employer>
    <job-area>Краснодар</job-area>
    <job-url>https://vakansa24.ru/vacancy.html?id=135500339</job-url>
    <job-date>2026-07-23 06:25</job-date>
    <salary><from>150000</from><to>500000</to><currency>RUR</currency></salary>
    <job-description><![CDATA[Описание отсутствует]]></job-description>
  </job>
  <job>
    <job-id>134755216</job-id>
    <job-title>Менеджер по работе с сетями (e-commerce)</job-title>
    <job-employer>Апиценна</job-employer>
    <job-area>Москва</job-area>
    <job-url>https://vakansa24.ru/vacancy.html?id=134755216</job-url>
    <job-date>2026-07-23 06:25</job-date>
    
    <job-description><![CDATA[Описание отсутствует]]></job-description>
  </job>
  <job>
    <job-id>135500338</job-id>
    <job-title>Продавец-консультант крупно-бытовой техники (ТРК Yolka)</job-title>
    <job-employer>Империя рекламы</job-employer>
    <job-area>Йошкар-Ола</job-area>
    <job-url>https://vakansa24.ru/vacancy.html?id=135500338</job-url>
    <job-date>2026-07-23 06:25</job-date>
    <salary><from>100000</from><to>150000</to><currency>RUR</currency></salary>
    <job-description><![CDATA[Описание отсутствует]]></job-description>
  </job>
  <job>
    <job-id>134665399</job-id>
    <job-title>Сотрудник на линию упаковки конфет и печенья (Ростов-на-Дону)</job-title>
    <job-employer>СИМПЛЕКС</job-employer>
    <job-area>Ставрополь</job-area>
    <job-url>https://vakansa24.ru/vacancy.html?id=134665399</job-url>
    <job-date>2026-07-23 06:25</job-date>
    <salary><from>142000</from><to>182600</to><currency>RUR</currency></salary>
    <job-description><![CDATA[Описание отсутствует]]></job-description>
  </job>
  <job>
    <job-id>135500336</job-id>
    <job-title>Врач анестезиолог-реаниматолог</job-title>
    <job-employer>КГБУЗ Ирбейская Районная Больница</job-employer>
    <job-area>Ирбейское</job-area>
    <job-url>https://vakansa24.ru/vacancy.html?id=135500336</job-url>
    <job-date>2026-07-23 06:25</job-date>
    <salary><from>111000</from><to>139841</to><currency>RUR</currency></salary>
    <job-description><![CDATA[Описание отсутствует]]></job-description>
  </job>
  <job>
    <job-id>135500337</job-id>
    <job-title>Врач анестезиолог-реаниматолог</job-title>
    <job-employer>КГБУЗ Ирбейская Районная Больница</job-employer>
    <job-area>Красноярск</job-area>
    <job-url>https://vakansa24.ru/vacancy.html?id=135500337</job-url>
    <job-date>2026-07-23 06:25</job-date>
    <salary><from>111000</from><to>139841</to><currency>RUR</currency></salary>
    <job-description><![CDATA[Описание отсутствует]]></job-description>
  </job>
  <job>
    <job-id>135500335</job-id>
    <job-title>Администратор</job-title>
    <job-employer>UroMed</job-employer>
    <job-area>Астрахань</job-area>
    <job-url>https://vakansa24.ru/vacancy.html?id=135500335</job-url>
    <job-date>2026-07-23 06:25</job-date>
    <salary><from>30000</from><to>45000</to><currency>RUR</currency></salary>
    <job-description><![CDATA[Описание отсутствует]]></job-description>
  </job>
  <job>
    <job-id>135374066</job-id>
    <job-title>Сотрудник (в центральный офис на Конди)</job-title>
    <job-employer>Дельтаинвест-Уфа</job-employer>
    <job-area>Уфа</job-area>
    <job-url>https://vakansa24.ru/vacancy.html?id=135374066</job-url>
    <job-date>2026-07-23 06:25</job-date>
    <salary><from>160000</from><to>225000</to><currency>RUR</currency></salary>
    <job-description><![CDATA[Описание отсутствует]]></job-description>
  </job>
  <job>
    <job-id>135411522</job-id>
    <job-title>Менеджер кафе (м. Мичуринский проспект)</job-title>
    <job-employer>Печорин Групп</job-employer>
    <job-area>Москва</job-area>
    <job-url>https://vakansa24.ru/vacancy.html?id=135411522</job-url>
    <job-date>2026-07-23 06:25</job-date>
    <salary><from>120000</from><currency>RUR</currency></salary>
    <job-description><![CDATA[Описание отсутствует]]></job-description>
  </job>
  <job>
    <job-id>129863592</job-id>
    <job-title>Учитель начальных классов</job-title>
    <job-employer>ОАНО Сколка</job-employer>
    <job-area>Москва</job-area>
    <job-url>https://vakansa24.ru/vacancy.html?id=129863592</job-url>
    <job-date>2026-07-23 06:25</job-date>
    
    <job-description><![CDATA[Описание отсутствует]]></job-description>
  </job>
  <job>
    <job-id>130057380</job-id>
    <job-title>Руководитель индустрии ИТ</job-title>
    <job-employer>ОАНО Сколка</job-employer>
    <job-area>Москва</job-area>
    <job-url>https://vakansa24.ru/vacancy.html?id=130057380</job-url>
    <job-date>2026-07-23 06:25</job-date>
    
    <job-description><![CDATA[Описание отсутствует]]></job-description>
  </job>
  <job>
    <job-id>131010300</job-id>
    <job-title>Заведующий кафедрой биологии и химии / Методист</job-title>
    <job-employer>ОАНО Сколка</job-employer>
    <job-area>Москва</job-area>
    <job-url>https://vakansa24.ru/vacancy.html?id=131010300</job-url>
    <job-date>2026-07-23 06:25</job-date>
    
    <job-description><![CDATA[Описание отсутствует]]></job-description>
  </job>
  <job>
    <job-id>131467769</job-id>
    <job-title>Лаборант в студию кулинарных экспериментов</job-title>
    <job-employer>ОАНО Сколка</job-employer>
    <job-area>Москва</job-area>
    <job-url>https://vakansa24.ru/vacancy.html?id=131467769</job-url>
    <job-date>2026-07-23 06:25</job-date>
    <salary><from>73500</from><currency>RUR</currency></salary>
    <job-description><![CDATA[Описание отсутствует]]></job-description>
  </job>
  <job>
    <job-id>132126517</job-id>
    <job-title>Руководитель образовательного проекта</job-title>
    <job-employer>ОАНО Сколка</job-employer>
    <job-area>Москва</job-area>
    <job-url>https://vakansa24.ru/vacancy.html?id=132126517</job-url>
    <job-date>2026-07-23 06:25</job-date>
    
    <job-description><![CDATA[Описание отсутствует]]></job-description>
  </job>
  <job>
    <job-id>132401658</job-id>
    <job-title>Преподаватель географии в школу СКОЛКА</job-title>
    <job-employer>ОАНО Сколка</job-employer>
    <job-area>Москва</job-area>
    <job-url>https://vakansa24.ru/vacancy.html?id=132401658</job-url>
    <job-date>2026-07-23 06:25</job-date>
    
    <job-description><![CDATA[Описание отсутствует]]></job-description>
  </job>
  <job>
    <job-id>132402795</job-id>
    <job-title>Преподаватель математики в школу СКОЛКА</job-title>
    <job-employer>ОАНО Сколка</job-employer>
    <job-area>Москва</job-area>
    <job-url>https://vakansa24.ru/vacancy.html?id=132402795</job-url>
    <job-date>2026-07-23 06:25</job-date>
    
    <job-description><![CDATA[Описание отсутствует]]></job-description>
  </job>
  <job>
    <job-id>132424114</job-id>
    <job-title>Преподаватель информатики в школу СКОЛКА</job-title>
    <job-employer>ОАНО Сколка</job-employer>
    <job-area>Москва</job-area>
    <job-url>https://vakansa24.ru/vacancy.html?id=132424114</job-url>
    <job-date>2026-07-23 06:25</job-date>
    
    <job-description><![CDATA[Описание отсутствует]]></job-description>
  </job>
  <job>
    <job-id>132631390</job-id>
    <job-title>Методист / Заведующий кафедрой физической культуры</job-title>
    <job-employer>ОАНО Сколка</job-employer>
    <job-area>Москва</job-area>
    <job-url>https://vakansa24.ru/vacancy.html?id=132631390</job-url>
    <job-date>2026-07-23 06:25</job-date>
    
    <job-description><![CDATA[Описание отсутствует]]></job-description>
  </job>
  <job>
    <job-id>133495311</job-id>
    <job-title>Ассистент руководителя (лаборант) в лабораторию физики / Инженер-техник</job-title>
    <job-employer>ОАНО Сколка</job-employer>
    <job-area>Москва</job-area>
    <job-url>https://vakansa24.ru/vacancy.html?id=133495311</job-url>
    <job-date>2026-07-23 06:25</job-date>
    
    <job-description><![CDATA[Описание отсутствует]]></job-description>
  </job>
  <job>
    <job-id>133975904</job-id>
    <job-title>Воспитатель ГПД (1-4 классы)</job-title>
    <job-employer>ОАНО Сколка</job-employer>
    <job-area>Москва</job-area>
    <job-url>https://vakansa24.ru/vacancy.html?id=133975904</job-url>
    <job-date>2026-07-23 06:25</job-date>
    
    <job-description><![CDATA[Описание отсутствует]]></job-description>
  </job>
  <job>
    <job-id>134281499</job-id>
    <job-title>Тьютор (5 класс)</job-title>
    <job-employer>ОАНО Сколка</job-employer>
    <job-area>Москва</job-area>
    <job-url>https://vakansa24.ru/vacancy.html?id=134281499</job-url>
    <job-date>2026-07-23 06:25</job-date>
    <salary><from>126000</from><currency>RUR</currency></salary>
    <job-description><![CDATA[Описание отсутствует]]></job-description>
  </job>
  <job>
    <job-id>134294232</job-id>
    <job-title>Воспитатель ГПД (5 классы)</job-title>
    <job-employer>ОАНО Сколка</job-employer>
    <job-area>Москва</job-area>
    <job-url>https://vakansa24.ru/vacancy.html?id=134294232</job-url>
    <job-date>2026-07-23 06:25</job-date>
    
    <job-description><![CDATA[Описание отсутствует]]></job-description>
  </job>
  <job>
    <job-id>134542651</job-id>
    <job-title>Главный продюсер</job-title>
    <job-employer>ОАНО Сколка</job-employer>
    <job-area>Москва</job-area>
    <job-url>https://vakansa24.ru/vacancy.html?id=134542651</job-url>
    <job-date>2026-07-23 06:25</job-date>
    
    <job-description><![CDATA[Описание отсутствует]]></job-description>
  </job>
  <job>
    <job-id>134586537</job-id>
    <job-title>Директор департамента обеспечения и эксплуатации</job-title>
    <job-employer>ОАНО Сколка</job-employer>
    <job-area>Москва</job-area>
    <job-url>https://vakansa24.ru/vacancy.html?id=134586537</job-url>
    <job-date>2026-07-23 06:25</job-date>
    
    <job-description><![CDATA[Описание отсутствует]]></job-description>
  </job>
  <job>
    <job-id>134946801</job-id>
    <job-title>Директор по маркетингу (CMO)</job-title>
    <job-employer>ОАНО Сколка</job-employer>
    <job-area>Москва</job-area>
    <job-url>https://vakansa24.ru/vacancy.html?id=134946801</job-url>
    <job-date>2026-07-23 06:25</job-date>
    
    <job-description><![CDATA[Описание отсутствует]]></job-description>
  </job>
  <job>
    <job-id>135158632</job-id>
    <job-title>Заместитель директора по образованию</job-title>
    <job-employer>ОАНО Сколка</job-employer>
    <job-area>Москва</job-area>
    <job-url>https://vakansa24.ru/vacancy.html?id=135158632</job-url>
    <job-date>2026-07-23 06:25</job-date>
    
    <job-description><![CDATA[Описание отсутствует]]></job-description>
  </job>
  <job>
    <job-id>135228750</job-id>
    <job-title>Тьютор средние/старшие классы</job-title>
    <job-employer>ОАНО Сколка</job-employer>
    <job-area>Москва</job-area>
    <job-url>https://vakansa24.ru/vacancy.html?id=135228750</job-url>
    <job-date>2026-07-23 06:25</job-date>
    
    <job-description><![CDATA[Описание отсутствует]]></job-description>
  </job>
  <job>
    <job-id>135478826</job-id>
    <job-title>Ведущий специалист проектов по текущим ремонтам</job-title>
    <job-employer>СОГАЗ</job-employer>
    <job-area>Москва</job-area>
    <job-url>https://vakansa24.ru/vacancy.html?id=135478826</job-url>
    <job-date>2026-07-23 06:25</job-date>
    
    <job-description><![CDATA[Описание отсутствует]]></job-description>
  </job>
  <job>
    <job-id>135500330</job-id>
    <job-title>Тайный покупатель</job-title>
    <job-employer>Сервизория</job-employer>
    <job-area>Печоры</job-area>
    <job-url>https://vakansa24.ru/vacancy.html?id=135500330</job-url>
    <job-date>2026-07-23 06:25</job-date>
    
    <job-description><![CDATA[Описание отсутствует]]></job-description>
  </job>
  <job>
    <job-id>133663741</job-id>
    <job-title>Плотник на отделочные работы</job-title>
    <job-employer>ЖБИ2-ИНВЕСТ</job-employer>
    <job-area>Воронеж</job-area>
    <job-url>https://vakansa24.ru/vacancy.html?id=133663741</job-url>
    <job-date>2026-07-23 06:25</job-date>
    <salary><from>100000</from><currency>RUR</currency></salary>
    <job-description><![CDATA[Описание отсутствует]]></job-description>
  </job>
  <job>
    <job-id>126415978</job-id>
    <job-title>Врач-физиотерапевт (м. Ул. 1905г)</job-title>
    <job-employer>Поликлиника.ру</job-employer>
    <job-area>Москва</job-area>
    <job-url>https://vakansa24.ru/vacancy.html?id=126415978</job-url>
    <job-date>2026-07-23 06:25</job-date>
    <salary><from>202000</from><currency>RUR</currency></salary>
    <job-description><![CDATA[Описание отсутствует]]></job-description>
  </job>
  <job>
    <job-id>135500328</job-id>
    <job-title>Оператор линии полуфабрикатов</job-title>
    <job-employer>Черкизово, Группа предприятий</job-employer>
    <job-area>Янино-1</job-area>
    <job-url>https://vakansa24.ru/vacancy.html?id=135500328</job-url>
    <job-date>2026-07-23 06:25</job-date>
    <salary><from>70000</from><currency>RUR</currency></salary>
    <job-description><![CDATA[Описание отсутствует]]></job-description>
  </job>
  <job>
    <job-id>135500329</job-id>
    <job-title>Оператор линии полуфабрикатов</job-title>
    <job-employer>Черкизово, Группа предприятий</job-employer>
    <job-area>Всеволожск</job-area>
    <job-url>https://vakansa24.ru/vacancy.html?id=135500329</job-url>
    <job-date>2026-07-23 06:25</job-date>
    <salary><from>70000</from><currency>RUR</currency></salary>
    <job-description><![CDATA[Описание отсутствует]]></job-description>
  </job>
  <job>
    <job-id>135433391</job-id>
    <job-title>Повар в кафе (метро Мичуринский проспект)</job-title>
    <job-employer>Печорин Групп</job-employer>
    <job-area>Москва</job-area>
    <job-url>https://vakansa24.ru/vacancy.html?id=135433391</job-url>
    <job-date>2026-07-23 06:25</job-date>
    <salary><from>6000</from><currency>RUR</currency></salary>
    <job-description><![CDATA[Описание отсутствует]]></job-description>
  </job>
  <job>
    <job-id>135500326</job-id>
    <job-title>Мастер строительного участка по электрике</job-title>
    <job-employer>А-Инжиниринг</job-employer>
    <job-area>Санкт-Петербург</job-area>
    <job-url>https://vakansa24.ru/vacancy.html?id=135500326</job-url>
    <job-date>2026-07-23 06:25</job-date>
    <salary><to>100000</to><currency>RUR</currency></salary>
    <job-description><![CDATA[Описание отсутствует]]></job-description>
  </job>
  <job>
    <job-id>135500325</job-id>
    <job-title>Координатор отдела продаж</job-title>
    <job-employer>СТИ</job-employer>
    <job-area>Москва</job-area>
    <job-url>https://vakansa24.ru/vacancy.html?id=135500325</job-url>
    <job-date>2026-07-23 06:25</job-date>
    <salary><from>100000</from><currency>RUR</currency></salary>
    <job-description><![CDATA[Описание отсутствует]]></job-description>
  </job>
  <job>
    <job-id>135500324</job-id>
    <job-title>Водитель-курьер на доставку (с личным автомобилем)</job-title>
    <job-employer>ROSSKO</job-employer>
    <job-area>Новый Уренгой</job-area>
    <job-url>https://vakansa24.ru/vacancy.html?id=135500324</job-url>
    <job-date>2026-07-23 06:25</job-date>
    <salary><from>94000</from><to>115000</to><currency>RUR</currency></salary>
    <job-description><![CDATA[Описание отсутствует]]></job-description>
  </job>
  <job>
    <job-id>135500322</job-id>
    <job-title>Специалист по охране труда</job-title>
    <job-employer>Bombbar (ООО Фитнес Фуд)</job-employer>
    <job-area>Тольятти</job-area>
    <job-url>https://vakansa24.ru/vacancy.html?id=135500322</job-url>
    <job-date>2026-07-23 06:25</job-date>
    
    <job-description><![CDATA[Описание отсутствует]]></job-description>
  </job>
  <job>
    <job-id>135500316</job-id>
    <job-title>Руководитель трансфера технологий синтеза АФС (GMP, фармпроизводство)</job-title>
    <job-employer>АВВА РУС</job-employer>
    <job-area>Киров (Кировская область)</job-area>
    <job-url>https://vakansa24.ru/vacancy.html?id=135500316</job-url>
    <job-date>2026-07-23 06:25</job-date>
    
    <job-description><![CDATA[Описание отсутствует]]></job-description>
  </job>
  <job>
    <job-id>135500317</job-id>
    <job-title>Руководитель трансфера технологий синтеза АФС (GMP, фармпроизводство)</job-title>
    <job-employer>АВВА РУС</job-employer>
    <job-area>Москва</job-area>
    <job-url>https://vakansa24.ru/vacancy.html?id=135500317</job-url>
    <job-date>2026-07-23 06:25</job-date>
    
    <job-description><![CDATA[Описание отсутствует]]></job-description>
  </job>
  <job>
    <job-id>135500318</job-id>
    <job-title>Руководитель трансфера технологий синтеза АФС (GMP, фармпроизводство)</job-title>
    <job-employer>АВВА РУС</job-employer>
    <job-area>Санкт-Петербург</job-area>
    <job-url>https://vakansa24.ru/vacancy.html?id=135500318</job-url>
    <job-date>2026-07-23 06:25</job-date>
    
    <job-description><![CDATA[Описание отсутствует]]></job-description>
  </job>
  <job>
    <job-id>135500319</job-id>
    <job-title>Руководитель трансфера технологий синтеза АФС (GMP, фармпроизводство)</job-title>
    <job-employer>АВВА РУС</job-employer>
    <job-area>Новосибирск</job-area>
    <job-url>https://vakansa24.ru/vacancy.html?id=135500319</job-url>
    <job-date>2026-07-23 06:25</job-date>
    
    <job-description><![CDATA[Описание отсутствует]]></job-description>
  </job>
  <job>
    <job-id>135500320</job-id>
    <job-title>Руководитель трансфера технологий синтеза АФС (GMP, фармпроизводство)</job-title>
    <job-employer>АВВА РУС</job-employer>
    <job-area>Екатеринбург</job-area>
    <job-url>https://vakansa24.ru/vacancy.html?id=135500320</job-url>
    <job-date>2026-07-23 06:25</job-date>
    
    <job-description><![CDATA[Описание отсутствует]]></job-description>
  </job>
  <job>
    <job-id>135500321</job-id>
    <job-title>Руководитель трансфера технологий синтеза АФС (GMP, фармпроизводство)</job-title>
    <job-employer>АВВА РУС</job-employer>
    <job-area>Казань</job-area>
    <job-url>https://vakansa24.ru/vacancy.html?id=135500321</job-url>
    <job-date>2026-07-23 06:25</job-date>
    
    <job-description><![CDATA[Описание отсутствует]]></job-description>
  </job>
  <job>
    <job-id>134473359</job-id>
    <job-title>Помощник директора в ГМ &quot;ЛИНИЯ&quot;, г. Тамбов</job-title>
    <job-employer>ГРИНН, Корпорация</job-employer>
    <job-area>Тамбов</job-area>
    <job-url>https://vakansa24.ru/vacancy.html?id=134473359</job-url>
    <job-date>2026-07-23 06:25</job-date>
    <salary><from>29000</from><to>29000</to><currency>RUR</currency></salary>
    <job-description><![CDATA[Описание отсутствует]]></job-description>
  </job>
  <job>
    <job-id>135500315</job-id>
    <job-title>Продавец в продуктовый магазин</job-title>
    <job-employer>Сладкая жизнь, компания</job-employer>
    <job-area>Железнодорожный  (Московская область)</job-area>
    <job-url>https://vakansa24.ru/vacancy.html?id=135500315</job-url>
    <job-date>2026-07-23 06:25</job-date>
    <salary><from>76400</from><to>83600</to><currency>RUR</currency></salary>
    <job-description><![CDATA[Описание отсутствует]]></job-description>
  </job>
  <job>
    <job-id>135500313</job-id>
    <job-title>Врач-стоматолог-ортопед</job-title>
    <job-employer>КГБУЗ Ирбейская Районная Больница</job-employer>
    <job-area>Ирбейское</job-area>
    <job-url>https://vakansa24.ru/vacancy.html?id=135500313</job-url>
    <job-date>2026-07-23 06:25</job-date>
    <salary><from>50000</from><to>666266</to><currency>RUR</currency></salary>
    <job-description><![CDATA[Описание отсутствует]]></job-description>
  </job>
  <job>
    <job-id>135500314</job-id>
    <job-title>Врач-стоматолог-ортопед</job-title>
    <job-employer>КГБУЗ Ирбейская Районная Больница</job-employer>
    <job-area>Красноярск</job-area>
    <job-url>https://vakansa24.ru/vacancy.html?id=135500314</job-url>
    <job-date>2026-07-23 06:25</job-date>
    <salary><from>50000</from><to>666266</to><currency>RUR</currency></salary>
    <job-description><![CDATA[Описание отсутствует]]></job-description>
  </job>
  <job>
    <job-id>135500312</job-id>
    <job-title>Сварщик на полуавтомат (металлоконструкции)</job-title>
    <job-employer>АБТ-ГРУПП</job-employer>
    <job-area>Санкт-Петербург</job-area>
    <job-url>https://vakansa24.ru/vacancy.html?id=135500312</job-url>
    <job-date>2026-07-23 06:25</job-date>
    <salary><from>105000</from><to>130000</to><currency>RUR</currency></salary>
    <job-description><![CDATA[Описание отсутствует]]></job-description>
  </job>
  <job>
    <job-id>135500311</job-id>
    <job-title>Системный администратор</job-title>
    <job-employer>РСК</job-employer>
    <job-area>Туапсе</job-area>
    <job-url>https://vakansa24.ru/vacancy.html?id=135500311</job-url>
    <job-date>2026-07-23 06:25</job-date>
    <salary><from>80000</from><to>100000</to><currency>RUR</currency></salary>
    <job-description><![CDATA[Описание отсутствует]]></job-description>
  </job>
  <job>
    <job-id>135174378</job-id>
    <job-title>Повар в кафе (метро Народное ополчение)</job-title>
    <job-employer>Печорин Групп</job-employer>
    <job-area>Москва</job-area>
    <job-url>https://vakansa24.ru/vacancy.html?id=135174378</job-url>
    <job-date>2026-07-23 06:25</job-date>
    <salary><from>96000</from><to>108000</to><currency>RUR</currency></salary>
    <job-description><![CDATA[Описание отсутствует]]></job-description>
  </job>
  <job>
    <job-id>134691627</job-id>
    <job-title>Мойщица/мойщик посуды</job-title>
    <job-employer>Пельменная (ИП Прыкин Игорь Петрович)</job-employer>
    <job-area>Челябинск</job-area>
    <job-url>https://vakansa24.ru/vacancy.html?id=134691627</job-url>
    <job-date>2026-07-23 06:25</job-date>
    <salary><from>47000</from><to>55000</to><currency>RUR</currency></salary>
    <job-description><![CDATA[Описание отсутствует]]></job-description>
  </job>
  <job>
    <job-id>134668801</job-id>
    <job-title>Продавец-консультант ТЦ Эльград</job-title>
    <job-employer>Concept Group</job-employer>
    <job-area>Москва</job-area>
    <job-url>https://vakansa24.ru/vacancy.html?id=134668801</job-url>
    <job-date>2026-07-23 06:25</job-date>
    <salary><from>70000</from><currency>RUR</currency></salary>
    <job-description><![CDATA[Описание отсутствует]]></job-description>
  </job>
  <job>
    <job-id>135500310</job-id>
    <job-title>Консультант нотариуса</job-title>
    <job-employer>Нотариус Вишина Ольга Борисовна</job-employer>
    <job-area>Москва</job-area>
    <job-url>https://vakansa24.ru/vacancy.html?id=135500310</job-url>
    <job-date>2026-07-23 06:25</job-date>
    <salary><from>70000</from><to>100000</to><currency>RUR</currency></salary>
    <job-description><![CDATA[Описание отсутствует]]></job-description>
  </job>
  <job>
    <job-id>135500309</job-id>
    <job-title>Менеджер по тендерам (развитие сети)</job-title>
    <job-employer>Белоусов Михаил Алексеевич</job-employer>
    <job-area>Балашиха (Московская область)</job-area>
    <job-url>https://vakansa24.ru/vacancy.html?id=135500309</job-url>
    <job-date>2026-07-23 06:25</job-date>
    <salary><from>70000</from><to>175000</to><currency>RUR</currency></salary>
    <job-description><![CDATA[Описание отсутствует]]></job-description>
  </job>
  <job>
    <job-id>135500308</job-id>
    <job-title>Менеджер интернет-магазина</job-title>
    <job-employer>X-Com</job-employer>
    <job-area>Смоленск</job-area>
    <job-url>https://vakansa24.ru/vacancy.html?id=135500308</job-url>
    <job-date>2026-07-23 06:25</job-date>
    <salary><from>55000</from><to>80000</to><currency>RUR</currency></salary>
    <job-description><![CDATA[Описание отсутствует]]></job-description>
  </job>
  <job>
    <job-id>135500307</job-id>
    <job-title>Старший дежурный инженер инфраструктуры (ЦОД)</job-title>
    <job-employer>Московский филиал АО ЦентрИнформ</job-employer>
    <job-area>Москва</job-area>
    <job-url>https://vakansa24.ru/vacancy.html?id=135500307</job-url>
    <job-date>2026-07-23 06:25</job-date>
    
    <job-description><![CDATA[Описание отсутствует]]></job-description>
  </job>
  <job>
    <job-id>135500306</job-id>
    <job-title>Финансовый директор (CFO)</job-title>
    <job-employer>МБМ Девелопмент</job-employer>
    <job-area>Москва</job-area>
    <job-url>https://vakansa24.ru/vacancy.html?id=135500306</job-url>
    <job-date>2026-07-23 06:25</job-date>
    
    <job-description><![CDATA[Описание отсутствует]]></job-description>
  </job>
  <job>
    <job-id>135204664</job-id>
    <job-title>Комплектовщик на склад (ночной график 2/2)</job-title>
    <job-employer>Миофарм</job-employer>
    <job-area>Истра (Московская область)</job-area>
    <job-url>https://vakansa24.ru/vacancy.html?id=135204664</job-url>
    <job-date>2026-07-23 06:25</job-date>
    <salary><from>120000</from><currency>RUR</currency></salary>
    <job-description><![CDATA[Описание отсутствует]]></job-description>
  </job>
  <job>
    <job-id>135500305</job-id>
    <job-title>Водитель бензовоза</job-title>
    <job-employer>Томскнефтепродукт</job-employer>
    <job-area>Томск</job-area>
    <job-url>https://vakansa24.ru/vacancy.html?id=135500305</job-url>
    <job-date>2026-07-23 06:25</job-date>
    <salary><from>80000</from><currency>RUR</currency></salary>
    <job-description><![CDATA[Описание отсутствует]]></job-description>
  </job>
  <job>
    <job-id>132191789</job-id>
    <job-title>Медицинская сестра/Медицинский брат в преаналитику</job-title>
    <job-employer>Смарт Мед Лаб</job-employer>
    <job-area>Краснодар</job-area>
    <job-url>https://vakansa24.ru/vacancy.html?id=132191789</job-url>
    <job-date>2026-07-23 06:25</job-date>
    <salary><from>30000</from><to>40000</to><currency>RUR</currency></salary>
    <job-description><![CDATA[Описание отсутствует]]></job-description>
  </job>
  <job>
    <job-id>135011102</job-id>
    <job-title>Администратор медицинской клиники</job-title>
    <job-employer>Смарт Мед Лаб</job-employer>
    <job-area>Краснодар</job-area>
    <job-url>https://vakansa24.ru/vacancy.html?id=135011102</job-url>
    <job-date>2026-07-23 06:25</job-date>
    <salary><from>45000</from><to>55000</to><currency>RUR</currency></salary>
    <job-description><![CDATA[Описание отсутствует]]></job-description>
  </job>
  <job>
    <job-id>135331076</job-id>
    <job-title>Продавец-кассир АЗС Солнечногорск (д.Снопово М-11, 63 км)</job-title>
    <job-employer>Сеть АЗС «Газпромнефть» / ООО «Газпромнефть-Центр»</job-employer>
    <job-area>Солнечногорск (Московская область)</job-area>
    <job-url>https://vakansa24.ru/vacancy.html?id=135331076</job-url>
    <job-date>2026-07-23 06:25</job-date>
    <salary><from>90000</from><currency>RUR</currency></salary>
    <job-description><![CDATA[Описание отсутствует]]></job-description>
  </job>
  <job>
    <job-id>135500302</job-id>
    <job-title>Руководитель департамента логистики</job-title>
    <job-employer>Транспортная Группа Континент</job-employer>
    <job-area>Новосибирск</job-area>
    <job-url>https://vakansa24.ru/vacancy.html?id=135500302</job-url>
    <job-date>2026-07-23 06:25</job-date>
    
    <job-description><![CDATA[Описание отсутствует]]></job-description>
  </job>
</jobs>